pyfi/__init__.py
pyfi/common.py
pyfi/data_agent.py
pyfi/filter.py
pyfi/mapper.py
pyfi/ncd.py
pyfi/visual.py
pyfi/wind_helper.py
pyfi/wind_helper_test.py
pyfi/backtest/__init__.py
pyfi/backtest/monthly_backtest.py
pyfi/backtest/performance_curve.py
pyfi/backtest/performance_pct.py
pyfi/function/__init__.py
pyfi/function/bond.py
pyfi/function/bootstrap_yield_curve.py
pyfi/function/curve_performance.py
pyfi/function/eqd_performance.py
pyfi/function/lunar.py
pyfi/function/performance.py
pyfi/function/statistics.py
pyfi/function/timeseries.py
pyfi_helper-0.1.23.dist-info/METADATA
pyfi_helper-0.1.23.dist-info/WHEEL
pyfi_helper-0.1.23.dist-info/top_level.txt
pyfi_helper-0.1.23.dist-info/zip-safe
pyfi_helper-0.1.23.dist-info/RECORD
