Metadata-Version: 2.1
Name: pyfi-helper
Version: 0.1.23
Summary: encapsulate the windPy API with pandas
Home-page: https://github.com/wangluzhou/pyfi.git
Author: wangluzhou
Author-email: wangluzhou@aliyun.com
License: MIT
Platform: UNKNOWN
Requires-Dist: pandas
Requires-Dist: matplotlib
Requires-Dist: scipy
